{":ohos:ImagePickerOhos:default@PreBuild":{"_inputs":[{"dataType":"ValueEntry","value":"{\"_name\":\"BUILTIN_TASK_COMMAND\",\"_value\":\"\",\"_valueType\":\"string\",\"_hash\":\"0b5d05294fdf4e78e8482ef53eb64ac0\"}"},{"dataType":"ValueEntry","value":"{\"_name\":\"BUILTIN_TASK_ENV\",\"_value\":\"\",\"_valueType\":\"string\",\"_hash\":\"cdcdc2ec8062ca9ec1de46dbf2bbc053\"}"},{"dataType":"ValueEntry","value":"{\"_name\":\"BUILTIN_TASK_TOOLCHAIN\",\"_value\":\"\",\"_valueType\":\"string\",\"_hash\":\"e7f94a9422a8bc317a7d90b58efcb5f6\"}"},{"dataType":"ValueEntry","value":"{\"_name\":\"apiType\",\"_value\":\"stageMode\",\"_valueType\":\"string\",\"_hash\":\"699c7565645ea3ea8c88551a4926a3d5\"}"},{"dataType":"ValueEntry","value":"{\"_name\":\"codeType\",\"_value\":true,\"_valueType\":\"boolean\",\"_hash\":\"d6dcf21a9f078b661283507536e57ce8\"}"},{"dataType":"ValueEntry","value":"{\"_name\":\"compatibleApiVersion\",\"_value\":10,\"_valueType\":\"number\",\"_hash\":\"f08ac304243ae5663f2ea14e1973c253\"}"},{"dataType":"ValueEntry","value":"{\"_name\":\"compileApiVersion\",\"_value\":10,\"_valueType\":\"number\",\"_hash\":\"4fdb2d89c4c44dbf8c5dffe16d03220b\"}"},{"dataType":"ValueEntry","value":"{\"_name\":\"customTypes\",\"_value\":\"\",\"_valueType\":\"string\",\"_hash\":\"970a2695bffac1c5a4fa283dc36050e3\"}"},{"dataType":"ValueEntry","value":"{\"_name\":\"deviceType\",\"_value\":[\"default\"],\"_valueType\":\"object\",\"_hash\":\"251621b3aa815def41be8cbfc1a421e2\"}"},{"dataType":"ValueEntry","value":"{\"_name\":\"isSupportOhpmProj\",\"_value\":true,\"_valueType\":\"boolean\",\"_hash\":\"f3a249d7e3f751316e931b8a08b074b4\"}"},{"dataType":"ValueEntry","value":"{\"_name\":\"profileModuleName\",\"_value\":\"ImagePickerOhos\",\"_valueType\":\"string\",\"_hash\":\"7fcd9859068ddda92514c31ccbfa6296\"}"},{"dataType":"ValueEntry","value":"{\"_name\":\"sdkToolchainsComponentVersion\",\"_value\":\"4.0.0.40\",\"_valueType\":\"string\",\"_hash\":\"9822dc2efe3bc5434b273057d46ed8e2\"}"},{"dataType":"ValueEntry","value":"{\"_name\":\"targetStatusCode\",\"_value\":2,\"_valueType\":\"number\",\"_hash\":\"5a9255c0f4ee50904a9349ebafca8369\"}"}],"_successful":true,"_projectName":"ohos","_moduleName":"ImagePickerOhos","_taskName":"default@PreBuild","_key":":ohos:ImagePickerOhos:default@PreBuild","_executionId":":ohos:ImagePickerOhos:default@PreBuild:1698214704637","_inputFiles":{"dataType":"Map","value":[["D:\\project\\flutter-sig-package\\packages\\packages\\image_picker\\image_picker_ohos\\ohos\\AppScope\\app.json5",{"isDirectory":false,"fileSnapShotHashValue":"964e8d6450c00e1b37667dc7ff46a821"}],["D:\\project\\flutter-sig-package\\packages\\packages\\image_picker\\image_picker_ohos\\ohos\\image_picker\\src\\main\\module.json5",{"isDirectory":false,"fileSnapShotHashValue":"b5e5d1673c1252d2c7474d59551947ab"}],["D:\\project\\flutter-sig-package\\packages\\packages\\image_picker\\image_picker_ohos\\ohos\\image_picker\\oh-package.json5",{"fileSnapShotHashValue":"ebfddeb92a0a05ce9c19a548445f3840"}]]},"_outputFiles":{"dataType":"Map","value":[]}},":ohos:ImagePickerOhos:default@MergeProfile":{"_inputs":[{"dataType":"ValueEntry","value":"{\"_name\":\"BUILTIN_TASK_COMMAND\",\"_value\":\"\",\"_valueType\":\"string\",\"_hash\":\"0b5d05294fdf4e78e8482ef53eb64ac0\"}"},{"dataType":"ValueEntry","value":"{\"_name\":\"BUILTIN_TASK_ENV\",\"_value\":\"\",\"_valueType\":\"string\",\"_hash\":\"cdcdc2ec8062ca9ec1de46dbf2bbc053\"}"},{"dataType":"ValueEntry","value":"{\"_name\":\"BUILTIN_TASK_TOOLCHAIN\",\"_value\":\"\",\"_valueType\":\"string\",\"_hash\":\"e7f94a9422a8bc317a7d90b58efcb5f6\"}"},{"dataType":"ValueEntry","value":"{\"_name\":\"asanEnable\",\"_value\":false,\"_valueType\":\"boolean\",\"_hash\":\"bc2129ba20a21b7e5234139ede1b4d7b\"}"},{"dataType":"ValueEntry","value":"{\"_name\":\"buildRoot\",\"_value\":\"build\",\"_valueType\":\"string\",\"_hash\":\"4c2dd7bb7507f74001ec27f2936db7f9\"}"},{"dataType":"ValueEntry","value":"{\"_name\":\"compatibleSdkVersion\",\"_value\":10,\"_valueType\":\"number\",\"_hash\":\"8ca3e69374439355c4f1b77ba4fb3435\"}"},{"dataType":"ValueEntry","value":"{\"_name\":\"isDebug\",\"_value\":true,\"_valueType\":\"boolean\",\"_hash\":\"edbf05a2d2be2c385e75d9565a48d419\"}"},{"dataType":"ValueEntry","value":"{\"_name\":\"isHarModule\",\"_value\":true,\"_valueType\":\"boolean\",\"_hash\":\"02f77a1e25718bf2a5689a57185f47f6\"}"},{"dataType":"ValueEntry","value":"{\"_name\":\"multiProjects\",\"_value\":false,\"_valueType\":\"boolean\",\"_hash\":\"555604752defc243b4e4c55d1549fc06\"}"},{"dataType":"ValueEntry","value":"{\"_name\":\"releaseType\",\"_value\":\"Release\",\"_valueType\":\"string\",\"_hash\":\"bbcabdda034e97584f8c36f85b3ec517\"}"},{"dataType":"ValueEntry","value":"{\"_name\":\"targetSdkVersion\",\"_value\":10,\"_valueType\":\"number\",\"_hash\":\"68a4d173dd33897f0e74ffeae724b180\"}"}],"_successful":true,"_projectName":"ohos","_moduleName":"ImagePickerOhos","_taskName":"default@MergeProfile","_key":":ohos:ImagePickerOhos:default@MergeProfile","_executionId":":ohos:ImagePickerOhos:default@MergeProfile:1698214704726","_inputFiles":{"dataType":"Map","value":[["D:\\project\\flutter-sig-package\\packages\\packages\\image_picker\\image_picker_ohos\\ohos\\AppScope\\app.json5",{"fileSnapShotHashValue":"964e8d6450c00e1b37667dc7ff46a821"}],["D:\\project\\flutter-sig-package\\packages\\packages\\image_picker\\image_picker_ohos\\ohos\\image_picker\\src\\main\\module.json5",{"fileSnapShotHashValue":"b5e5d1673c1252d2c7474d59551947ab"}]]},"_outputFiles":{"dataType":"Map","value":[["D:\\project\\flutter-sig-package\\packages\\packages\\image_picker\\image_picker_ohos\\ohos\\image_picker\\build\\default\\intermediates\\merge_profile\\default\\module.json",{"fileSnapShotHashValue":"5d787e0d2a955682a8ed3e2000e23942"}]]}},":ohos:ImagePickerOhos:default@ProcessProfile":{"_inputs":[{"dataType":"ValueEntry","value":"{\"_name\":\"BUILTIN_TASK_COMMAND\",\"_value\":\"\",\"_valueType\":\"string\",\"_hash\":\"0b5d05294fdf4e78e8482ef53eb64ac0\"}"},{"dataType":"ValueEntry","value":"{\"_name\":\"BUILTIN_TASK_ENV\",\"_value\":\"\",\"_valueType\":\"string\",\"_hash\":\"cdcdc2ec8062ca9ec1de46dbf2bbc053\"}"},{"dataType":"ValueEntry","value":"{\"_name\":\"BUILTIN_TASK_TOOLCHAIN\",\"_value\":\"\",\"_valueType\":\"string\",\"_hash\":\"e7f94a9422a8bc317a7d90b58efcb5f6\"}"},{"dataType":"ValueEntry","value":"{\"_name\":\"arkEnable\",\"_value\":true,\"_valueType\":\"boolean\",\"_hash\":\"750b4bda198545a67903dfb3f6a00a95\"}"},{"dataType":"ValueEntry","value":"{\"_name\":\"compileMode\",\"_value\":\"esmodule\",\"_valueType\":\"string\",\"_hash\":\"dacafc8e0b77a950178a0b4d142dc32c\"}"},{"dataType":"ValueEntry","value":"{\"_name\":\"dependency\",\"_value\":\"[]\",\"_valueType\":\"string\",\"_hash\":\"ac54f3d4ced2d4c1d666d40e4f7c454a\"}"},{"dataType":"ValueEntry","value":"{\"_name\":\"deviceTypes\",\"_value\":[\"default\"],\"_valueType\":\"object\",\"_hash\":\"a011e14018d30eaaa9aadcb99f2c07e3\"}"}],"_successful":true,"_projectName":"ohos","_moduleName":"ImagePickerOhos","_taskName":"default@ProcessProfile","_key":":ohos:ImagePickerOhos:default@ProcessProfile","_executionId":":ohos:ImagePickerOhos:default@ProcessProfile:1698214704729","_inputFiles":{"dataType":"Map","value":[["D:\\project\\flutter-sig-package\\packages\\packages\\image_picker\\image_picker_ohos\\ohos\\image_picker\\build\\default\\intermediates\\merge_profile\\default\\module.json",{"fileSnapShotHashValue":"5d787e0d2a955682a8ed3e2000e23942"}]]},"_outputFiles":{"dataType":"Map","value":[["D:\\project\\flutter-sig-package\\packages\\packages\\image_picker\\image_picker_ohos\\ohos\\image_picker\\build\\default\\intermediates\\process_profile\\default\\module.json",{"fileSnapShotHashValue":"8939812e1f7fc610131db22dbf71e2b8"}]]}},":ohos:ImagePickerOhos:default@ProcessResource":{"_inputs":[{"dataType":"ValueEntry","value":"{\"_name\":\"BUILTIN_TASK_COMMAND\",\"_value\":\"\",\"_valueType\":\"string\",\"_hash\":\"0b5d05294fdf4e78e8482ef53eb64ac0\"}"},{"dataType":"ValueEntry","value":"{\"_name\":\"BUILTIN_TASK_ENV\",\"_value\":\"\",\"_valueType\":\"string\",\"_hash\":\"cdcdc2ec8062ca9ec1de46dbf2bbc053\"}"},{"dataType":"ValueEntry","value":"{\"_name\":\"BUILTIN_TASK_TOOLCHAIN\",\"_value\":\"\",\"_valueType\":\"string\",\"_hash\":\"e7f94a9422a8bc317a7d90b58efcb5f6\"}"},{"dataType":"ValueEntry","value":"{\"_name\":\"resConfigJsonContent\",\"_value\":\"{\\\"configPath\\\":\\\"D:\\\\\\\\project\\\\\\\\flutter-sig-package\\\\\\\\packages\\\\\\\\packages\\\\\\\\image_picker\\\\\\\\image_picker_ohos\\\\\\\\ohos\\\\\\\\image_picker\\\\\\\\build\\\\\\\\default\\\\\\\\intermediates\\\\\\\\process_profile\\\\\\\\default\\\\\\\\module.json\\\",\\\"packageName\\\":\\\"com.example.image_picker_ohos\\\",\\\"output\\\":\\\"D:\\\\\\\\project\\\\\\\\flutter-sig-package\\\\\\\\packages\\\\\\\\packages\\\\\\\\image_picker\\\\\\\\image_picker_ohos\\\\\\\\ohos\\\\\\\\image_picker\\\\\\\\build\\\\\\\\default\\\\\\\\intermediates\\\\\\\\res\\\\\\\\default\\\",\\\"moduleNames\\\":\\\"ImagePickerOhos\\\",\\\"ResourceTable\\\":[\\\"D:\\\\\\\\project\\\\\\\\flutter-sig-package\\\\\\\\packages\\\\\\\\packages\\\\\\\\image_picker\\\\\\\\image_picker_ohos\\\\\\\\ohos\\\\\\\\image_picker\\\\\\\\build\\\\\\\\default\\\\\\\\generated\\\\\\\\r\\\\\\\\default\\\\\\\\ResourceTable.h\\\"],\\\"moduleResources\\\":[\\\"D:\\\\\\\\project\\\\\\\\flutter-sig-package\\\\\\\\packages\\\\\\\\packages\\\\\\\\image_picker\\\\\\\\image_picker_ohos\\\\\\\\ohos\\\\\\\\image_picker\\\\\\\\src\\\\\\\\main\\\\\\\\resources\\\"],\\\"dependencies\\\":[],\\\"ids\\\":\\\"D:\\\\\\\\project\\\\\\\\flutter-sig-package\\\\\\\\packages\\\\\\\\packages\\\\\\\\image_picker\\\\\\\\image_picker_ohos\\\\\\\\ohos\\\\\\\\image_picker\\\\\\\\build\\\\\\\\default\\\\\\\\intermediates\\\\\\\\res\\\\\\\\default\\\\\\\\ids_map\\\",\\\"definedIds\\\":\\\"D:\\\\\\\\project\\\\\\\\flutter-sig-package\\\\\\\\packages\\\\\\\\packages\\\\\\\\image_picker\\\\\\\\image_picker_ohos\\\\\\\\ohos\\\\\\\\image_picker\\\\\\\\build\\\\\\\\default\\\\\\\\intermediates\\\\\\\\res\\\\\\\\default\\\\\\\\ids_map\\\\\\\\id_defined.json\\\"}\",\"_valueType\":\"string\",\"_hash\":\"094ba2ab134b043afb8cceafd5d7b424\"}"}],"_successful":true,"_projectName":"ohos","_moduleName":"ImagePickerOhos","_taskName":"default@ProcessResource","_key":":ohos:ImagePickerOhos:default@ProcessResource","_executionId":":ohos:ImagePickerOhos:default@ProcessResource:1698214704800","_inputFiles":{"dataType":"Map","value":[]},"_outputFiles":{"dataType":"Map","value":[["D:\\project\\flutter-sig-package\\packages\\packages\\image_picker\\image_picker_ohos\\ohos\\image_picker\\build\\default\\intermediates\\res\\default\\resConfig.json",{"isDirectory":false,"fileSnapShotHashValue":"8c7d45011877c56a72fcb807ebb6bc2b"}]]}},":ohos:ImagePickerOhos:default@ProcessLibs":{"_inputs":[{"dataType":"ValueEntry","value":"{\"_name\":\"BUILTIN_TASK_COMMAND\",\"_value\":\"\",\"_valueType\":\"string\",\"_hash\":\"0b5d05294fdf4e78e8482ef53eb64ac0\"}"},{"dataType":"ValueEntry","value":"{\"_name\":\"BUILTIN_TASK_ENV\",\"_value\":\"\",\"_valueType\":\"string\",\"_hash\":\"cdcdc2ec8062ca9ec1de46dbf2bbc053\"}"},{"dataType":"ValueEntry","value":"{\"_name\":\"BUILTIN_TASK_TOOLCHAIN\",\"_value\":\"\",\"_valueType\":\"string\",\"_hash\":\"e7f94a9422a8bc317a7d90b58efcb5f6\"}"}],"_successful":true,"_projectName":"ohos","_moduleName":"ImagePickerOhos","_taskName":"default@ProcessLibs","_key":":ohos:ImagePickerOhos:default@ProcessLibs","_executionId":":ohos:ImagePickerOhos:default@ProcessLibs:1698214704802","_inputFiles":{"dataType":"Map","value":[["D:\\project\\flutter-sig-package\\packages\\packages\\image_picker\\image_picker_ohos\\ohos\\image_picker\\libs",{"isDirectory":true,"fileSnapShotHashValue":"10e79cafa6077f7d3eaa1b186ca64629"}]]},"_outputFiles":{"dataType":"Map","value":[["D:\\project\\flutter-sig-package\\packages\\packages\\image_picker\\image_picker_ohos\\ohos\\image_picker\\build\\default\\intermediates\\libs\\default",{"isDirectory":true,"fileSnapShotHashValue":""}]]}},":ohos:ImagePickerOhos:default@CompileResource":{"_inputs":[{"dataType":"ValueEntry","value":"{\"_name\":\"BUILTIN_TASK_COMMAND\",\"_value\":\"D:\\\\tools\\\\devecostudio-windows-4.0.3.601\\\\devecostudio-windows-4.0.3.601\\\\sdk\\\\WinSDK\\\\openharmony\\\\10\\\\toolchains\\\\restool.exe,-l,D:\\\\project\\\\flutter-sig-package\\\\packages\\\\packages\\\\image_picker\\\\image_picker_ohos\\\\ohos\\\\image_picker\\\\build\\\\default\\\\intermediates\\\\res\\\\default\\\\resConfig.json\",\"_valueType\":\"string\",\"_hash\":\"14c801d64188624db77c83dba61dba39\"}"},{"dataType":"ValueEntry","value":"{\"_name\":\"BUILTIN_TASK_ENV\",\"_value\":\"\",\"_valueType\":\"string\",\"_hash\":\"cdcdc2ec8062ca9ec1de46dbf2bbc053\"}"},{"dataType":"ValueEntry","value":"{\"_name\":\"BUILTIN_TASK_TOOLCHAIN\",\"_value\":\"D:\\\\tools\\\\devecostudio-windows-4.0.3.601\\\\devecostudio-windows-4.0.3.601\\\\sdk\\\\WinSDK\\\\openharmony\\\\10\\\\toolchains\\\\restool.exe\",\"_valueType\":\"string\",\"_hash\":\"f0f12dfd8cd033c0eb8fb3c260197576\"}"},{"dataType":"ValueEntry","value":"{\"_name\":\"TARGET_CONFIG\",\"_value\":\"{\\\"name\\\":\\\"default\\\",\\\"runtimeOS\\\":\\\"HarmonyOS\\\"}\",\"_valueType\":\"string\",\"_hash\":\"d1734598343a94c88ec5404fdcdfa944\"}"}],"_successful":true,"_projectName":"ohos","_moduleName":"ImagePickerOhos","_taskName":"default@CompileResource","_key":":ohos:ImagePickerOhos:default@CompileResource","_executionId":":ohos:ImagePickerOhos:default@CompileResource:1698214704805","_inputFiles":{"dataType":"Map","value":[["D:\\project\\flutter-sig-package\\packages\\packages\\image_picker\\image_picker_ohos\\ohos\\image_picker\\src\\main\\resources",{"fileSnapShotHashValue":"207026386988c767f552382ae165688e"}],["D:\\project\\flutter-sig-package\\packages\\packages\\image_picker\\image_picker_ohos\\ohos\\image_picker\\build\\default\\intermediates\\process_profile\\default\\module.json",{"isDirectory":false,"fileSnapShotHashValue":"8939812e1f7fc610131db22dbf71e2b8"}],["D:\\project\\flutter-sig-package\\packages\\packages\\image_picker\\image_picker_ohos\\ohos\\image_picker\\build\\default\\intermediates\\res\\default\\resConfig.json",{"isDirectory":false,"fileSnapShotHashValue":"8c7d45011877c56a72fcb807ebb6bc2b"}]]},"_outputFiles":{"dataType":"Map","value":[["D:\\project\\flutter-sig-package\\packages\\packages\\image_picker\\image_picker_ohos\\ohos\\image_picker\\build\\default\\intermediates\\res\\default",{"isDirectory":true,"fileSnapShotHashValue":"3a9c8541c8d21bc0b857c9540d4d73cd"}],["D:\\project\\flutter-sig-package\\packages\\packages\\image_picker\\image_picker_ohos\\ohos\\image_picker\\build\\default\\generated\\r\\default\\ResourceTable.h",{"isDirectory":false,"fileSnapShotHashValue":"1153f8d21c2af81b11c4ed39a072ee10"}],["D:\\project\\flutter-sig-package\\packages\\packages\\image_picker\\image_picker_ohos\\ohos\\image_picker\\build\\default\\generated\\r\\default",{"isDirectory":true,"fileSnapShotHashValue":"d0723379ba685b5b718eb3e8301ca915"}]]}},":ohos:ImagePickerOhos:default@PackageHar":{"_inputs":[{"dataType":"ValueEntry","value":"{\"_name\":\"hasNativeOption\",\"_value\":false,\"_valueType\":\"boolean\"}"},{"dataType":"ValueEntry","value":"{\"_name\":\"needCppTypes\",\"_value\":false,\"_valueType\":\"boolean\"}"},{"dataType":"ValueEntry","value":"{\"_name\":\"harModuleJson\",\"_value\":\"D:\\\\project\\\\flutter-sig-package\\\\packages\\\\packages\\\\image_picker\\\\image_picker_ohos\\\\ohos\\\\image_picker\\\\build\\\\default\\\\cache\\\\default\\\\default@PackageHar\\\\src\\\\main\\\\module.json5\",\"_valueType\":\"string\"}"},{"dataType":"ValueEntry","value":"{\"_name\":\"isOhpmProject\",\"_value\":true,\"_valueType\":\"boolean\"}"},{"dataType":"ValueEntry","value":"{\"_name\":\"artifactType\",\"_value\":\"original\",\"_valueType\":\"string\"}"},{"dataType":"ValueEntry","value":"{\"_name\":\"BUILTIN_TASK_COMMAND\",\"_value\":\"C:\\\\Users\\\\z30010942\\\\nodejs\\\\npm.cmd,pack\",\"_valueType\":\"string\"}"},{"dataType":"ValueEntry","value":"{\"_name\":\"BUILTIN_TASK_TOOLCHAIN\",\"_value\":\"\",\"_valueType\":\"string\"}"},{"dataType":"ValueEntry","value":"{\"_name\":\"BUILTIN_TASK_ENV\",\"_value\":\"cwd:D:\\\\project\\\\flutter-sig-package\\\\packages\\\\packages\\\\image_picker\\\\image_picker_ohos\\\\ohos\\\\image_picker\\\\build\\\\default\\\\cache\\\\default\\\\default@PackageHar;\",\"_valueType\":\"string\"}"}],"_successful":true,"_projectName":"ohos","_moduleName":"ImagePickerOhos","_taskName":"default@PackageHar","_key":":ohos:ImagePickerOhos:default@PackageHar","_executionId":":ohos:ImagePickerOhos:default@PackageHar:1698215363784","_inputFiles":{"dataType":"Map","value":[["D:\\project\\flutter-sig-package\\packages\\packages\\image_picker\\image_picker_ohos\\ohos\\image_picker\\build\\default\\intermediates\\merge_profile\\default",{"isDirectory":true,"fileSnapShotHashValue":"ff428b484cbfcea8a88034509079ea05"}],["D:\\project\\flutter-sig-package\\packages\\packages\\image_picker\\image_picker_ohos\\ohos\\image_picker",{"isDirectory":true,"test":{"dataType":"RegExp","value":"^(?!D:\\\\project\\\\flutter-sig-package\\\\packages\\\\packages\\\\image_picker\\\\image_picker_ohos\\\\ohos\\\\image_picker\\\\libs|D:\\\\project\\\\flutter-sig-package\\\\packages\\\\packages\\\\image_picker\\\\image_picker_ohos\\\\ohos\\\\image_picker\\\\build|D:\\\\project\\\\flutter-sig-package\\\\packages\\\\packages\\\\image_picker\\\\image_picker_ohos\\\\ohos\\\\image_picker\\\\node_modules|D:\\\\project\\\\flutter-sig-package\\\\packages\\\\packages\\\\image_picker\\\\image_picker_ohos\\\\ohos\\\\image_picker\\\\oh_modules|D:\\\\project\\\\flutter-sig-package\\\\packages\\\\packages\\\\image_picker\\\\image_picker_ohos\\\\ohos\\\\image_picker\\\\.cxx|D:\\\\project\\\\flutter-sig-package\\\\packages\\\\packages\\\\image_picker\\\\image_picker_ohos\\\\ohos\\\\image_picker\\\\.previewer|D:\\\\project\\\\flutter-sig-package\\\\packages\\\\packages\\\\image_picker\\\\image_picker_ohos\\\\ohos\\\\image_picker\\\\.hvigor|D:\\\\project\\\\flutter-sig-package\\\\packages\\\\packages\\\\image_picker\\\\image_picker_ohos\\\\ohos\\\\image_picker\\\\.gitignore|D:\\\\project\\\\flutter-sig-package\\\\packages\\\\packages\\\\image_picker\\\\image_picker_ohos\\\\ohos\\\\image_picker\\\\.ohpmignore).*"},"fileSnapShotHashValue":"1c03ab9caf59f1dd7ad8dbe319e4f2f2"}],["D:\\project\\flutter-sig-package\\packages\\packages\\image_picker\\image_picker_ohos\\ohos\\image_picker\\build\\default\\intermediates\\libs\\default",{"isDirectory":true,"fileSnapShotHashValue":""}],["D:\\project\\flutter-sig-package\\packages\\packages\\image_picker\\image_picker_ohos\\ohos\\image_picker\\build\\default\\intermediates\\res\\default\\ResourceTable.txt",{"isDirectory":false,"fileSnapShotHashValue":"83daafbc996f8c7b3f3e6c161f2c15dc"}]]},"_outputFiles":{"dataType":"Map","value":[["D:\\project\\flutter-sig-package\\packages\\packages\\image_picker\\image_picker_ohos\\ohos\\image_picker\\build\\default\\cache\\default\\default@PackageHar",{"isDirectory":true,"fileSnapShotHashValue":"9588af00be29b670520499e25ddf7a89"}],["D:\\project\\flutter-sig-package\\packages\\packages\\image_picker\\image_picker_ohos\\ohos\\image_picker\\build\\default\\outputs\\default",{"isDirectory":true,"fileSnapShotHashValue":"6cdbd408caf10dc143c0418805911463"}]]}}}